watchman_http_server/__init__.py
watchman_http_server/commands.py
watchman_http_server/main.py
watchman_http_server/config/__init__.py
watchman_http_server/config/api_key.py
watchman_http_server/config/settings.py
watchman_http_server-0.5.9.dist-info/METADATA
watchman_http_server-0.5.9.dist-info/WHEEL
watchman_http_server-0.5.9.dist-info/entry_points.txt
watchman_http_server-0.5.9.dist-info/top_level.txt
watchman_http_server-0.5.9.dist-info/RECORD
