Metadata-Version: 2.4
Name: watchman_http_server
Version: 0.5.9
Summary: Un serveur HTTP FastAPI pour récupérer les applications installées
Author: Watchman
Author-email: support@watchman.bj
Classifier: Programming Language :: Python :: 3
Classifier: Framework :: FastAPI
Classifier: Operating System :: OS Independent
Requires-Python: >=3.7
Requires-Dist: annotated-types==0.7.0
Requires-Dist: anyio==4.9.0
Requires-Dist: APScheduler==3.11.0
Requires-Dist: click==8.2.1
Requires-Dist: colorama==0.4.6
Requires-Dist: django-environ==0.12.0
Requires-Dist: fastapi==0.115.12
Requires-Dist: getmac==0.9.5
Requires-Dist: h11==0.16.0
Requires-Dist: idna==3.10
Requires-Dist: psutil==7.0.0
Requires-Dist: pydantic==2.11.5
Requires-Dist: pydantic_core==2.33.2
Requires-Dist: python-dotenv==1.1.0
Requires-Dist: setuptools==80.8.0
Requires-Dist: sniffio==1.3.1
Requires-Dist: starlette==0.46.2
Requires-Dist: typing-inspection==0.4.1
Requires-Dist: typing_extensions==4.13.2
Requires-Dist: tzdata==2025.2
Requires-Dist: tzlocal==5.3.1
Requires-Dist: uvicorn==0.34.2
Dynamic: author
Dynamic: author-email
Dynamic: classifier
Dynamic: description
Dynamic: description-content-type
Dynamic: requires-dist
Dynamic: requires-python
Dynamic: summary
